{
  "schemaVersion" : "1.0",
  "name" : "output-file-sdsm",
  "variables" : [ "D:\\desktop\\git-data\\depends\\27f1206a1aab12fc321a4993bc6b199789f767d5\\new\\src\\main\\java\\dependsDependsCommand.java", "D:\\desktop\\git-data\\depends\\27f1206a1aab12fc321a4993bc6b199789f767d5\\new\\src\\main\\java\\dependsMain.java", "D:\\desktop\\git-data\\depends\\27f1206a1aab12fc321a4993bc6b199789f767d5\\new\\src\\main\\java\\depends\\generatorDependencyGenerator.java", "D:\\desktop\\git-data\\depends\\27f1206a1aab12fc321a4993bc6b199789f767d5\\new\\src\\main\\java\\depends\\generatorFileDependencyGenerator.java", "D:\\desktop\\git-data\\depends\\27f1206a1aab12fc321a4993bc6b199789f767d5\\new\\src\\main\\java\\depends\\generatorFunctionDependencyGenerator.java", "D:\\desktop\\git-data\\depends\\27f1206a1aab12fc321a4993bc6b199789f767d5\\new\\src\\main\\java\\depends\\generatorStructureDependencyGenerator.java" ],
  "cells" : [ {
    "src" : 1,
    "dest" : 4,
    "values" : {
      "Call" : 1.0,
      "Import" : 1.0,
      "Use" : 1.0,
      "Create" : 1.0
    }
  }, {
    "src" : 1,
    "dest" : 3,
    "values" : {
      "Call" : 1.0,
      "Import" : 1.0,
      "Use" : 1.0,
      "Create" : 1.0
    }
  }, {
    "src" : 1,
    "dest" : 2,
    "values" : {
      "Call" : 5.0,
      "Import" : 1.0,
      "Use" : 2.0,
      "Parameter" : 2.0,
      "Contain" : 2.0
    }
  }, {
    "src" : 3,
    "dest" : 2,
    "values" : {
      "Extend" : 1.0,
      "Use" : 2.0
    }
  }, {
    "src" : 1,
    "dest" : 0,
    "values" : {
      "Call" : 37.0,
      "Create" : 3.0,
      "Use" : 1.0,
      "Parameter" : 3.0,
      "Contain" : 1.0
    }
  }, {
    "src" : 5,
    "dest" : 2,
    "values" : {
      "Extend" : 1.0
    }
  }, {
    "src" : 4,
    "dest" : 2,
    "values" : {
      "Extend" : 1.0,
      "Use" : 3.0
    }
  }, {
    "src" : 1,
    "dest" : 5,
    "values" : {
      "Call" : 1.0,
      "Import" : 1.0,
      "Use" : 1.0,
      "Create" : 1.0
    }
  } ]
}