{
  "schemaVersion" : "1.0",
  "name" : "output-file-sdsm",
  "variables" : [ "D:\\desktop\\git-data\\depends\\ce24334dfe3996db900e2dac3024f0ada2221ad9\\old\\src\\main\\java\\depends\\Main.java", "D:\\desktop\\git-data\\depends\\ce24334dfe3996db900e2dac3024f0ada2221ad9\\old\\src\\main\\java\\depends\\addons\\DV8MappingFileBuilder.java", "D:\\desktop\\git-data\\depends\\ce24334dfe3996db900e2dac3024f0ada2221ad9\\old\\src\\main\\java\\depends\\entity\\Expression.java", "D:\\desktop\\git-data\\depends\\ce24334dfe3996db900e2dac3024f0ada2221ad9\\old\\src\\main\\java\\depends\\entity\\types\\AnonymousBlock.java", "D:\\desktop\\git-data\\depends\\ce24334dfe3996db900e2dac3024f0ada2221ad9\\old\\src\\main\\java\\depends\\entity\\types\\FileEntity.java", "D:\\desktop\\git-data\\depends\\ce24334dfe3996db900e2dac3024f0ada2221ad9\\old\\src\\main\\java\\depends\\extractor\\AbstractLangWorker.java", "D:\\desktop\\git-data\\depends\\ce24334dfe3996db900e2dac3024f0ada2221ad9\\old\\src\\main\\java\\depends\\extractor\\cpp\\CppFileParser.java", "D:\\desktop\\git-data\\depends\\ce24334dfe3996db900e2dac3024f0ada2221ad9\\old\\src\\main\\java\\depends\\extractor\\cpp\\CppImportLookupStrategy.java", "D:\\desktop\\git-data\\depends\\ce24334dfe3996db900e2dac3024f0ada2221ad9\\old\\src\\main\\java\\depends\\extractor\\cpp\\CppWorker.java", "D:\\desktop\\git-data\\depends\\ce24334dfe3996db900e2dac3024f0ada2221ad9\\old\\src\\main\\java\\depends\\extractor\\cpp\\cdt\\ASTStringUtil.java", "D:\\desktop\\git-data\\depends\\ce24334dfe3996db900e2dac3024f0ada2221ad9\\old\\src\\main\\java\\depends\\extractor\\cpp\\cdt\\CDTParser.java", "D:\\desktop\\git-data\\depends\\ce24334dfe3996db900e2dac3024f0ada2221ad9\\old\\src\\main\\java\\depends\\extractor\\cpp\\cdt\\CdtCppEntitiesListener.java", "D:\\desktop\\git-data\\depends\\ce24334dfe3996db900e2dac3024f0ada2221ad9\\old\\src\\main\\java\\depends\\extractor\\cpp\\cdt\\ExpressionUsage.java", "D:\\desktop\\git-data\\depends\\ce24334dfe3996db900e2dac3024f0ada2221ad9\\old\\src\\main\\java\\depends\\extractor\\java\\JavaWorker.java", "D:\\desktop\\git-data\\depends\\ce24334dfe3996db900e2dac3024f0ada2221ad9\\old\\src\\main\\java\\depends\\extractor\\java\\context\\AnnotationProcessor.java", "D:\\desktop\\git-data\\depends\\ce24334dfe3996db900e2dac3024f0ada2221ad9\\old\\src\\main\\java\\depends\\extractor\\java\\context\\ClassTypeContextHelper.java", "D:\\desktop\\git-data\\depends\\ce24334dfe3996db900e2dac3024f0ada2221ad9\\old\\src\\main\\java\\depends\\extractor\\java\\context\\ExpressionUsage.java", "D:\\desktop\\git-data\\depends\\ce24334dfe3996db900e2dac3024f0ada2221ad9\\old\\src\\main\\java\\depends\\extractor\\java\\context\\FormalParameterListContextHelper.java", "D:\\desktop\\git-data\\depends\\ce24334dfe3996db900e2dac3024f0ada2221ad9\\old\\src\\main\\java\\depends\\extractor\\java\\context\\VariableDeclaratorsContextHelper.java", "D:\\desktop\\git-data\\depends\\ce24334dfe3996db900e2dac3024f0ada2221ad9\\old\\src\\main\\java\\depends\\format\\json\\JDataBuilder.java", "D:\\desktop\\git-data\\depends\\ce24334dfe3996db900e2dac3024f0ada2221ad9\\old\\src\\main\\java\\depends\\format\\matrix\\DependencyMatrix.java", "D:\\desktop\\git-data\\depends\\ce24334dfe3996db900e2dac3024f0ada2221ad9\\old\\src\\main\\java\\depends\\format\\matrix\\FileDependencyGenerator.java", "D:\\desktop\\git-data\\depends\\ce24334dfe3996db900e2dac3024f0ada2221ad9\\old\\src\\main\\java\\depends\\format\\xml\\XDataBuilder.java", "D:\\desktop\\git-data\\depends\\ce24334dfe3996db900e2dac3024f0ada2221ad9\\old\\src\\test\\java\\depends\\extractor\\cpp\\cdt\\CppExpressionTest.java", "D:\\desktop\\git-data\\depends\\ce24334dfe3996db900e2dac3024f0ada2221ad9\\old\\src\\test\\java\\depends\\extractor\\cpp\\cdt\\CppParameterParserTest.java", "D:\\desktop\\git-data\\depends\\ce24334dfe3996db900e2dac3024f0ada2221ad9\\old\\src\\test\\java\\depends\\extractor\\cpp\\cdt\\ForwardDeclareTest.java", "D:\\desktop\\git-data\\depends\\ce24334dfe3996db900e2dac3024f0ada2221ad9\\old\\src\\test\\java\\depends\\extractor\\cpp\\cdt\\IncludeRelationTest.java", "D:\\desktop\\git-data\\depends\\ce24334dfe3996db900e2dac3024f0ada2221ad9\\old\\src\\test\\java\\depends\\extractor\\cpp\\cdt\\UsingTest.java", "D:\\desktop\\git-data\\depends\\ce24334dfe3996db900e2dac3024f0ada2221ad9\\old\\src\\test\\java\\depends\\extractor\\cpp\\cdt\\extendsTest.java" ],
  "cells" : [ {
    "src" : 22,
    "dest" : 20,
    "values" : {
      "Call" : 2.0,
      "Import" : 1.0,
      "Parameter" : 1.0
    }
  }, {
    "src" : 12,
    "dest" : 2,
    "values" : {
      "Call" : 1.0,
      "Import" : 1.0,
      "Create" : 1.0,
      "Use" : 27.0,
      "Parameter" : 1.0,
      "Contain" : 2.0
    }
  }, {
    "src" : 5,
    "dest" : 20,
    "values" : {
      "Import" : 1.0,
      "Return" : 1.0,
      "Use" : 1.0,
      "Contain" : 1.0
    }
  }, {
    "src" : 5,
    "dest" : 21,
    "values" : {
      "Call" : 2.0,
      "Import" : 1.0,
      "Use" : 1.0,
      "Create" : 1.0
    }
  }, {
    "src" : 25,
    "dest" : 6,
    "values" : {
      "Import" : 1.0,
      "Contain" : 1.0
    }
  }, {
    "src" : 5,
    "dest" : 22,
    "values" : {
      "Call" : 2.0,
      "Import" : 1.0,
      "Create" : 1.0,
      "Contain" : 1.0
    }
  }, {
    "src" : 21,
    "dest" : 4,
    "values" : {
      "Cast" : 1.0,
      "Import" : 1.0,
      "Use" : 1.0
    }
  }, {
    "src" : 25,
    "dest" : 21,
    "values" : {
      "Call" : 2.0,
      "Import" : 1.0,
      "Create" : 1.0,
      "Contain" : 1.0
    }
  }, {
    "src" : 25,
    "dest" : 20,
    "values" : {
      "Import" : 1.0,
      "Contain" : 1.0
    }
  }, {
    "src" : 12,
    "dest" : 9,
    "values" : {
      "Call" : 3.0,
      "Use" : 3.0
    }
  }, {
    "src" : 7,
    "dest" : 4,
    "values" : {
      "Cast" : 4.0,
      "Call" : 4.0,
      "Import" : 1.0,
      "Use" : 2.0,
      "Parameter" : 1.0,
      "Contain" : 1.0
    }
  }, {
    "src" : 19,
    "dest" : 20,
    "values" : {
      "Call" : 2.0,
      "Import" : 1.0,
      "Parameter" : 1.0
    }
  }, {
    "src" : 16,
    "dest" : 2,
    "values" : {
      "Call" : 1.0,
      "Import" : 1.0,
      "Create" : 1.0,
      "Use" : 30.0,
      "Parameter" : 1.0,
      "Contain" : 2.0
    }
  }, {
    "src" : 21,
    "dest" : 20,
    "values" : {
      "Call" : 4.0,
      "Return" : 2.0,
      "Create" : 1.0,
      "Contain" : 2.0
    }
  }, {
    "src" : 11,
    "dest" : 9,
    "values" : {
      "Call" : 5.0,
      "Use" : 5.0
    }
  }, {
    "src" : 24,
    "dest" : 6,
    "values" : {
      "Import" : 1.0,
      "Contain" : 1.0
    }
  }, {
    "src" : 11,
    "dest" : 12,
    "values" : {
      "Call" : 2.0,
      "Use" : 1.0,
      "Create" : 1.0,
      "Contain" : 1.0
    }
  }, {
    "src" : 28,
    "dest" : 6,
    "values" : {
      "Import" : 1.0,
      "Contain" : 1.0
    }
  }, {
    "src" : 8,
    "dest" : 5,
    "values" : {
      "Call" : 2.0,
      "Import" : 1.0,
      "Extend" : 1.0,
      "Use" : 5.0
    }
  }, {
    "src" : 17,
    "dest" : 15,
    "values" : {
      "Call" : 1.0,
      "Use" : 1.0
    }
  }, {
    "src" : 0,
    "dest" : 13,
    "values" : {
      "Call" : 1.0,
      "Import" : 1.0,
      "Create" : 1.0
    }
  }, {
    "src" : 23,
    "dest" : 6,
    "values" : {
      "Import" : 1.0,
      "Contain" : 1.0
    }
  }, {
    "src" : 5,
    "dest" : 19,
    "values" : {
      "Call" : 2.0,
      "Import" : 1.0,
      "Create" : 1.0,
      "Contain" : 1.0
    }
  }, {
    "src" : 0,
    "dest" : 8,
    "values" : {
      "Call" : 1.0,
      "Import" : 1.0,
      "Create" : 1.0
    }
  }, {
    "src" : 27,
    "dest" : 6,
    "values" : {
      "Import" : 1.0,
      "Contain" : 2.0
    }
  }, {
    "src" : 13,
    "dest" : 5,
    "values" : {
      "Call" : 1.0,
      "Import" : 1.0,
      "Extend" : 1.0,
      "Use" : 4.0
    }
  }, {
    "src" : 16,
    "dest" : 15,
    "values" : {
      "Call" : 1.0,
      "Use" : 1.0
    }
  }, {
    "src" : 8,
    "dest" : 7,
    "values" : {
      "Call" : 1.0,
      "Create" : 1.0
    }
  }, {
    "src" : 26,
    "dest" : 6,
    "values" : {
      "Import" : 1.0,
      "Contain" : 4.0
    }
  }, {
    "src" : 0,
    "dest" : 5,
    "values" : {
      "Call" : 4.0,
      "Import" : 1.0,
      "Contain" : 1.0
    }
  } ]
}