{
    "nodes": [
        "D:\\desktop\\git-data\\depends\\5ddfc9e8ec6791a95895138f084e042cd116ff8b\\old\\src\\main\\java\\depends\\extractor\\AbstractLangProcessor.java",
        "D:\\desktop\\git-data\\depends\\5ddfc9e8ec6791a95895138f084e042cd116ff8b\\old\\src\\main\\java\\depends\\extractor\\cpp\\CppImportLookupStrategy.java",
        "D:\\desktop\\git-data\\depends\\5ddfc9e8ec6791a95895138f084e042cd116ff8b\\old\\src\\main\\java\\depends\\extractor\\cpp\\CppProcessor.java",
        "D:\\desktop\\git-data\\depends\\5ddfc9e8ec6791a95895138f084e042cd116ff8b\\old\\src\\main\\java\\depends\\extractor\\empty\\EmptyImportLookupStategy.java",
        "D:\\desktop\\git-data\\depends\\5ddfc9e8ec6791a95895138f084e042cd116ff8b\\old\\src\\main\\java\\depends\\extractor\\golang\\GoImportLookupStrategy.java",
        "D:\\desktop\\git-data\\depends\\5ddfc9e8ec6791a95895138f084e042cd116ff8b\\old\\src\\main\\java\\depends\\extractor\\golang\\GoProcessor.java",
        "D:\\desktop\\git-data\\depends\\5ddfc9e8ec6791a95895138f084e042cd116ff8b\\old\\src\\main\\java\\depends\\extractor\\java\\JavaImportLookupStrategy.java",
        "D:\\desktop\\git-data\\depends\\5ddfc9e8ec6791a95895138f084e042cd116ff8b\\old\\src\\main\\java\\depends\\extractor\\java\\JavaProcessor.java",
        "D:\\desktop\\git-data\\depends\\5ddfc9e8ec6791a95895138f084e042cd116ff8b\\old\\src\\main\\java\\depends\\extractor\\kotlin\\KotlinProcessor.java",
        "D:\\desktop\\git-data\\depends\\5ddfc9e8ec6791a95895138f084e042cd116ff8b\\old\\src\\main\\java\\depends\\extractor\\pom\\PomImportLookupStategy.java",
        "D:\\desktop\\git-data\\depends\\5ddfc9e8ec6791a95895138f084e042cd116ff8b\\old\\src\\main\\java\\depends\\extractor\\pom\\PomProcessor.java",
        "D:\\desktop\\git-data\\depends\\5ddfc9e8ec6791a95895138f084e042cd116ff8b\\old\\src\\main\\java\\depends\\extractor\\python\\BasePythonProcessor.java",
        "D:\\desktop\\git-data\\depends\\5ddfc9e8ec6791a95895138f084e042cd116ff8b\\old\\src\\main\\java\\depends\\extractor\\python\\PythonImportLookupStrategy.java",
        "D:\\desktop\\git-data\\depends\\5ddfc9e8ec6791a95895138f084e042cd116ff8b\\old\\src\\main\\java\\depends\\extractor\\ruby\\RubyImportLookupStrategy.java",
        "D:\\desktop\\git-data\\depends\\5ddfc9e8ec6791a95895138f084e042cd116ff8b\\old\\src\\main\\java\\depends\\extractor\\ruby\\RubyProcessor.java",
        "D:\\desktop\\git-data\\depends\\5ddfc9e8ec6791a95895138f084e042cd116ff8b\\old\\src\\main\\java\\depends\\relations\\ImportLookupStrategy.java",
        "D:\\desktop\\git-data\\depends\\5ddfc9e8ec6791a95895138f084e042cd116ff8b\\old\\src\\main\\java\\depends\\relations\\Inferer.java",
        "D:\\desktop\\git-data\\depends\\5ddfc9e8ec6791a95895138f084e042cd116ff8b\\old\\src\\test\\java\\depends\\extractor\\cpp\\CppParserTest.java",
        "D:\\desktop\\git-data\\depends\\5ddfc9e8ec6791a95895138f084e042cd116ff8b\\old\\src\\test\\java\\depends\\extractor\\golang\\GolangParserTest.java",
        "D:\\desktop\\git-data\\depends\\5ddfc9e8ec6791a95895138f084e042cd116ff8b\\old\\src\\test\\java\\depends\\extractor\\java\\JavaParserTest.java",
        "D:\\desktop\\git-data\\depends\\5ddfc9e8ec6791a95895138f084e042cd116ff8b\\old\\src\\test\\java\\depends\\extractor\\ruby\\RubyParserTest.java"
    ],
    "edges": [
        {
            "source": "D:\\desktop\\git-data\\depends\\5ddfc9e8ec6791a95895138f084e042cd116ff8b\\old\\src\\main\\java\\depends\\extractor\\AbstractLangProcessor.java",
            "target": "D:\\desktop\\git-data\\depends\\5ddfc9e8ec6791a95895138f084e042cd116ff8b\\old\\src\\main\\java\\depends\\relations\\ImportLookupStrategy.java",
            "label": "Import: 1.0, Return: 1.0, ",
            "Import": 1.0,
            "Return": 1.0
        },
        {
            "source": "D:\\desktop\\git-data\\depends\\5ddfc9e8ec6791a95895138f084e042cd116ff8b\\old\\src\\main\\java\\depends\\extractor\\AbstractLangProcessor.java",
            "target": "D:\\desktop\\git-data\\depends\\5ddfc9e8ec6791a95895138f084e042cd116ff8b\\old\\src\\main\\java\\depends\\relations\\Inferer.java",
            "label": "Call: 4.0, Import: 1.0, Use: 1.0, Create: 1.0, Contain: 1.0, ",
            "Call": 4.0,
            "Import": 1.0,
            "Use": 1.0,
            "Create": 1.0,
            "Contain": 1.0
        },
        {
            "source": "D:\\desktop\\git-data\\depends\\5ddfc9e8ec6791a95895138f084e042cd116ff8b\\old\\src\\main\\java\\depends\\extractor\\cpp\\CppImportLookupStrategy.java",
            "target": "D:\\desktop\\git-data\\depends\\5ddfc9e8ec6791a95895138f084e042cd116ff8b\\old\\src\\main\\java\\depends\\relations\\ImportLookupStrategy.java",
            "label": "Import: 1.0, Implement: 1.0, ",
            "Import": 1.0,
            "Implement": 1.0
        },
        {
            "source": "D:\\desktop\\git-data\\depends\\5ddfc9e8ec6791a95895138f084e042cd116ff8b\\old\\src\\main\\java\\depends\\extractor\\cpp\\CppImportLookupStrategy.java",
            "target": "D:\\desktop\\git-data\\depends\\5ddfc9e8ec6791a95895138f084e042cd116ff8b\\old\\src\\main\\java\\depends\\relations\\Inferer.java",
            "label": "Call: 2.0, Import: 1.0, Parameter: 1.0, ",
            "Call": 2.0,
            "Import": 1.0,
            "Parameter": 1.0
        },
        {
            "source": "D:\\desktop\\git-data\\depends\\5ddfc9e8ec6791a95895138f084e042cd116ff8b\\old\\src\\main\\java\\depends\\extractor\\cpp\\CppProcessor.java",
            "target": "D:\\desktop\\git-data\\depends\\5ddfc9e8ec6791a95895138f084e042cd116ff8b\\old\\src\\main\\java\\depends\\extractor\\AbstractLangProcessor.java",
            "label": "Call: 3.0, Import: 1.0, Extend: 1.0, Use: 7.0, ",
            "Call": 3.0,
            "Import": 1.0,
            "Extend": 1.0,
            "Use": 7.0
        },
        {
            "source": "D:\\desktop\\git-data\\depends\\5ddfc9e8ec6791a95895138f084e042cd116ff8b\\old\\src\\main\\java\\depends\\extractor\\cpp\\CppProcessor.java",
            "target": "D:\\desktop\\git-data\\depends\\5ddfc9e8ec6791a95895138f084e042cd116ff8b\\old\\src\\main\\java\\depends\\extractor\\cpp\\CppImportLookupStrategy.java",
            "label": "Call: 1.0, Create: 1.0, ",
            "Call": 1.0,
            "Create": 1.0
        },
        {
            "source": "D:\\desktop\\git-data\\depends\\5ddfc9e8ec6791a95895138f084e042cd116ff8b\\old\\src\\main\\java\\depends\\extractor\\cpp\\CppProcessor.java",
            "target": "D:\\desktop\\git-data\\depends\\5ddfc9e8ec6791a95895138f084e042cd116ff8b\\old\\src\\main\\java\\depends\\relations\\ImportLookupStrategy.java",
            "label": "Import: 1.0, Return: 1.0, ",
            "Import": 1.0,
            "Return": 1.0
        },
        {
            "source": "D:\\desktop\\git-data\\depends\\5ddfc9e8ec6791a95895138f084e042cd116ff8b\\old\\src\\main\\java\\depends\\extractor\\empty\\EmptyImportLookupStategy.java",
            "target": "D:\\desktop\\git-data\\depends\\5ddfc9e8ec6791a95895138f084e042cd116ff8b\\old\\src\\main\\java\\depends\\relations\\ImportLookupStrategy.java",
            "label": "Import: 1.0, Implement: 1.0, ",
            "Import": 1.0,
            "Implement": 1.0
        },
        {
            "source": "D:\\desktop\\git-data\\depends\\5ddfc9e8ec6791a95895138f084e042cd116ff8b\\old\\src\\main\\java\\depends\\extractor\\empty\\EmptyImportLookupStategy.java",
            "target": "D:\\desktop\\git-data\\depends\\5ddfc9e8ec6791a95895138f084e042cd116ff8b\\old\\src\\main\\java\\depends\\relations\\Inferer.java",
            "label": "Import: 1.0, Parameter: 1.0, ",
            "Import": 1.0,
            "Parameter": 1.0
        },
        {
            "source": "D:\\desktop\\git-data\\depends\\5ddfc9e8ec6791a95895138f084e042cd116ff8b\\old\\src\\main\\java\\depends\\extractor\\golang\\GoImportLookupStrategy.java",
            "target": "D:\\desktop\\git-data\\depends\\5ddfc9e8ec6791a95895138f084e042cd116ff8b\\old\\src\\main\\java\\depends\\relations\\ImportLookupStrategy.java",
            "label": "Import: 1.0, Implement: 1.0, ",
            "Import": 1.0,
            "Implement": 1.0
        },
        {
            "source": "D:\\desktop\\git-data\\depends\\5ddfc9e8ec6791a95895138f084e042cd116ff8b\\old\\src\\main\\java\\depends\\extractor\\golang\\GoImportLookupStrategy.java",
            "target": "D:\\desktop\\git-data\\depends\\5ddfc9e8ec6791a95895138f084e042cd116ff8b\\old\\src\\main\\java\\depends\\relations\\Inferer.java",
            "label": "Import: 1.0, Parameter: 1.0, ",
            "Import": 1.0,
            "Parameter": 1.0
        },
        {
            "source": "D:\\desktop\\git-data\\depends\\5ddfc9e8ec6791a95895138f084e042cd116ff8b\\old\\src\\main\\java\\depends\\extractor\\golang\\GoProcessor.java",
            "target": "D:\\desktop\\git-data\\depends\\5ddfc9e8ec6791a95895138f084e042cd116ff8b\\old\\src\\main\\java\\depends\\extractor\\AbstractLangProcessor.java",
            "label": "Call: 1.0, Import: 1.0, Extend: 1.0, Use: 2.0, ",
            "Call": 1.0,
            "Import": 1.0,
            "Extend": 1.0,
            "Use": 2.0
        },
        {
            "source": "D:\\desktop\\git-data\\depends\\5ddfc9e8ec6791a95895138f084e042cd116ff8b\\old\\src\\main\\java\\depends\\extractor\\golang\\GoProcessor.java",
            "target": "D:\\desktop\\git-data\\depends\\5ddfc9e8ec6791a95895138f084e042cd116ff8b\\old\\src\\main\\java\\depends\\extractor\\golang\\GoImportLookupStrategy.java",
            "label": "Call: 1.0, Create: 1.0, ",
            "Call": 1.0,
            "Create": 1.0
        },
        {
            "source": "D:\\desktop\\git-data\\depends\\5ddfc9e8ec6791a95895138f084e042cd116ff8b\\old\\src\\main\\java\\depends\\extractor\\golang\\GoProcessor.java",
            "target": "D:\\desktop\\git-data\\depends\\5ddfc9e8ec6791a95895138f084e042cd116ff8b\\old\\src\\main\\java\\depends\\relations\\ImportLookupStrategy.java",
            "label": "Import: 1.0, Return: 1.0, ",
            "Import": 1.0,
            "Return": 1.0
        },
        {
            "source": "D:\\desktop\\git-data\\depends\\5ddfc9e8ec6791a95895138f084e042cd116ff8b\\old\\src\\main\\java\\depends\\extractor\\java\\JavaImportLookupStrategy.java",
            "target": "D:\\desktop\\git-data\\depends\\5ddfc9e8ec6791a95895138f084e042cd116ff8b\\old\\src\\main\\java\\depends\\relations\\ImportLookupStrategy.java",
            "label": "Import: 1.0, Implement: 1.0, ",
            "Import": 1.0,
            "Implement": 1.0
        },
        {
            "source": "D:\\desktop\\git-data\\depends\\5ddfc9e8ec6791a95895138f084e042cd116ff8b\\old\\src\\main\\java\\depends\\extractor\\java\\JavaImportLookupStrategy.java",
            "target": "D:\\desktop\\git-data\\depends\\5ddfc9e8ec6791a95895138f084e042cd116ff8b\\old\\src\\main\\java\\depends\\relations\\Inferer.java",
            "label": "Import: 1.0, Parameter: 1.0, ",
            "Import": 1.0,
            "Parameter": 1.0
        },
        {
            "source": "D:\\desktop\\git-data\\depends\\5ddfc9e8ec6791a95895138f084e042cd116ff8b\\old\\src\\main\\java\\depends\\extractor\\java\\JavaProcessor.java",
            "target": "D:\\desktop\\git-data\\depends\\5ddfc9e8ec6791a95895138f084e042cd116ff8b\\old\\src\\main\\java\\depends\\extractor\\AbstractLangProcessor.java",
            "label": "Call: 1.0, Import: 1.0, Extend: 1.0, Use: 2.0, ",
            "Call": 1.0,
            "Import": 1.0,
            "Extend": 1.0,
            "Use": 2.0
        },
        {
            "source": "D:\\desktop\\git-data\\depends\\5ddfc9e8ec6791a95895138f084e042cd116ff8b\\old\\src\\main\\java\\depends\\extractor\\java\\JavaProcessor.java",
            "target": "D:\\desktop\\git-data\\depends\\5ddfc9e8ec6791a95895138f084e042cd116ff8b\\old\\src\\main\\java\\depends\\extractor\\java\\JavaImportLookupStrategy.java",
            "label": "Call: 1.0, Create: 1.0, ",
            "Call": 1.0,
            "Create": 1.0
        },
        {
            "source": "D:\\desktop\\git-data\\depends\\5ddfc9e8ec6791a95895138f084e042cd116ff8b\\old\\src\\main\\java\\depends\\extractor\\java\\JavaProcessor.java",
            "target": "D:\\desktop\\git-data\\depends\\5ddfc9e8ec6791a95895138f084e042cd116ff8b\\old\\src\\main\\java\\depends\\relations\\ImportLookupStrategy.java",
            "label": "Import: 1.0, Return: 1.0, ",
            "Import": 1.0,
            "Return": 1.0
        },
        {
            "source": "D:\\desktop\\git-data\\depends\\5ddfc9e8ec6791a95895138f084e042cd116ff8b\\old\\src\\main\\java\\depends\\extractor\\kotlin\\KotlinProcessor.java",
            "target": "D:\\desktop\\git-data\\depends\\5ddfc9e8ec6791a95895138f084e042cd116ff8b\\old\\src\\main\\java\\depends\\extractor\\AbstractLangProcessor.java",
            "label": "Call: 1.0, Import: 1.0, Extend: 1.0, Use: 2.0, ",
            "Call": 1.0,
            "Import": 1.0,
            "Extend": 1.0,
            "Use": 2.0
        },
        {
            "source": "D:\\desktop\\git-data\\depends\\5ddfc9e8ec6791a95895138f084e042cd116ff8b\\old\\src\\main\\java\\depends\\extractor\\kotlin\\KotlinProcessor.java",
            "target": "D:\\desktop\\git-data\\depends\\5ddfc9e8ec6791a95895138f084e042cd116ff8b\\old\\src\\main\\java\\depends\\extractor\\java\\JavaImportLookupStrategy.java",
            "label": "Call: 1.0, Import: 1.0, Create: 1.0, ",
            "Call": 1.0,
            "Import": 1.0,
            "Create": 1.0
        },
        {
            "source": "D:\\desktop\\git-data\\depends\\5ddfc9e8ec6791a95895138f084e042cd116ff8b\\old\\src\\main\\java\\depends\\extractor\\kotlin\\KotlinProcessor.java",
            "target": "D:\\desktop\\git-data\\depends\\5ddfc9e8ec6791a95895138f084e042cd116ff8b\\old\\src\\main\\java\\depends\\relations\\ImportLookupStrategy.java",
            "label": "Import: 1.0, Return: 1.0, ",
            "Import": 1.0,
            "Return": 1.0
        },
        {
            "source": "D:\\desktop\\git-data\\depends\\5ddfc9e8ec6791a95895138f084e042cd116ff8b\\old\\src\\main\\java\\depends\\extractor\\pom\\PomImportLookupStategy.java",
            "target": "D:\\desktop\\git-data\\depends\\5ddfc9e8ec6791a95895138f084e042cd116ff8b\\old\\src\\main\\java\\depends\\extractor\\empty\\EmptyImportLookupStategy.java",
            "label": "Import: 1.0, Extend: 1.0, ",
            "Import": 1.0,
            "Extend": 1.0
        },
        {
            "source": "D:\\desktop\\git-data\\depends\\5ddfc9e8ec6791a95895138f084e042cd116ff8b\\old\\src\\main\\java\\depends\\extractor\\pom\\PomProcessor.java",
            "target": "D:\\desktop\\git-data\\depends\\5ddfc9e8ec6791a95895138f084e042cd116ff8b\\old\\src\\main\\java\\depends\\extractor\\AbstractLangProcessor.java",
            "label": "Call: 2.0, Import: 1.0, Extend: 1.0, Use: 2.0, ",
            "Call": 2.0,
            "Import": 1.0,
            "Extend": 1.0,
            "Use": 2.0
        },
        {
            "source": "D:\\desktop\\git-data\\depends\\5ddfc9e8ec6791a95895138f084e042cd116ff8b\\old\\src\\main\\java\\depends\\extractor\\pom\\PomProcessor.java",
            "target": "D:\\desktop\\git-data\\depends\\5ddfc9e8ec6791a95895138f084e042cd116ff8b\\old\\src\\main\\java\\depends\\extractor\\pom\\PomImportLookupStategy.java",
            "label": "Call: 1.0, Create: 1.0, ",
            "Call": 1.0,
            "Create": 1.0
        },
        {
            "source": "D:\\desktop\\git-data\\depends\\5ddfc9e8ec6791a95895138f084e042cd116ff8b\\old\\src\\main\\java\\depends\\extractor\\pom\\PomProcessor.java",
            "target": "D:\\desktop\\git-data\\depends\\5ddfc9e8ec6791a95895138f084e042cd116ff8b\\old\\src\\main\\java\\depends\\relations\\ImportLookupStrategy.java",
            "label": "Import: 1.0, Return: 1.0, ",
            "Import": 1.0,
            "Return": 1.0
        },
        {
            "source": "D:\\desktop\\git-data\\depends\\5ddfc9e8ec6791a95895138f084e042cd116ff8b\\old\\src\\main\\java\\depends\\extractor\\python\\BasePythonProcessor.java",
            "target": "D:\\desktop\\git-data\\depends\\5ddfc9e8ec6791a95895138f084e042cd116ff8b\\old\\src\\main\\java\\depends\\extractor\\AbstractLangProcessor.java",
            "label": "Call: 1.0, Import: 1.0, Extend: 1.0, ",
            "Call": 1.0,
            "Import": 1.0,
            "Extend": 1.0
        },
        {
            "source": "D:\\desktop\\git-data\\depends\\5ddfc9e8ec6791a95895138f084e042cd116ff8b\\old\\src\\main\\java\\depends\\extractor\\python\\BasePythonProcessor.java",
            "target": "D:\\desktop\\git-data\\depends\\5ddfc9e8ec6791a95895138f084e042cd116ff8b\\old\\src\\main\\java\\depends\\extractor\\python\\PythonImportLookupStrategy.java",
            "label": "Call: 1.0, Use: 1.0, Create: 1.0, Contain: 1.0, ",
            "Call": 1.0,
            "Use": 1.0,
            "Create": 1.0,
            "Contain": 1.0
        },
        {
            "source": "D:\\desktop\\git-data\\depends\\5ddfc9e8ec6791a95895138f084e042cd116ff8b\\old\\src\\main\\java\\depends\\extractor\\python\\BasePythonProcessor.java",
            "target": "D:\\desktop\\git-data\\depends\\5ddfc9e8ec6791a95895138f084e042cd116ff8b\\old\\src\\main\\java\\depends\\relations\\ImportLookupStrategy.java",
            "label": "Import: 1.0, Return: 1.0, ",
            "Import": 1.0,
            "Return": 1.0
        },
        {
            "source": "D:\\desktop\\git-data\\depends\\5ddfc9e8ec6791a95895138f084e042cd116ff8b\\old\\src\\main\\java\\depends\\extractor\\python\\PythonImportLookupStrategy.java",
            "target": "D:\\desktop\\git-data\\depends\\5ddfc9e8ec6791a95895138f084e042cd116ff8b\\old\\src\\main\\java\\depends\\relations\\ImportLookupStrategy.java",
            "label": "Import: 1.0, Implement: 1.0, ",
            "Import": 1.0,
            "Implement": 1.0
        },
        {
            "source": "D:\\desktop\\git-data\\depends\\5ddfc9e8ec6791a95895138f084e042cd116ff8b\\old\\src\\main\\java\\depends\\extractor\\python\\PythonImportLookupStrategy.java",
            "target": "D:\\desktop\\git-data\\depends\\5ddfc9e8ec6791a95895138f084e042cd116ff8b\\old\\src\\main\\java\\depends\\relations\\Inferer.java",
            "label": "Import: 1.0, Parameter: 1.0, ",
            "Import": 1.0,
            "Parameter": 1.0
        },
        {
            "source": "D:\\desktop\\git-data\\depends\\5ddfc9e8ec6791a95895138f084e042cd116ff8b\\old\\src\\main\\java\\depends\\extractor\\ruby\\RubyImportLookupStrategy.java",
            "target": "D:\\desktop\\git-data\\depends\\5ddfc9e8ec6791a95895138f084e042cd116ff8b\\old\\src\\main\\java\\depends\\extractor\\cpp\\CppImportLookupStrategy.java",
            "label": "Import: 1.0, Extend: 1.0, ",
            "Import": 1.0,
            "Extend": 1.0
        },
        {
            "source": "D:\\desktop\\git-data\\depends\\5ddfc9e8ec6791a95895138f084e042cd116ff8b\\old\\src\\main\\java\\depends\\extractor\\ruby\\RubyProcessor.java",
            "target": "D:\\desktop\\git-data\\depends\\5ddfc9e8ec6791a95895138f084e042cd116ff8b\\old\\src\\main\\java\\depends\\extractor\\AbstractLangProcessor.java",
            "label": "Call: 2.0, Import: 1.0, Extend: 1.0, Use: 4.0, ",
            "Call": 2.0,
            "Import": 1.0,
            "Extend": 1.0,
            "Use": 4.0
        },
        {
            "source": "D:\\desktop\\git-data\\depends\\5ddfc9e8ec6791a95895138f084e042cd116ff8b\\old\\src\\main\\java\\depends\\extractor\\ruby\\RubyProcessor.java",
            "target": "D:\\desktop\\git-data\\depends\\5ddfc9e8ec6791a95895138f084e042cd116ff8b\\old\\src\\main\\java\\depends\\extractor\\ruby\\RubyImportLookupStrategy.java",
            "label": "Call: 1.0, Create: 1.0, ",
            "Call": 1.0,
            "Create": 1.0
        },
        {
            "source": "D:\\desktop\\git-data\\depends\\5ddfc9e8ec6791a95895138f084e042cd116ff8b\\old\\src\\main\\java\\depends\\extractor\\ruby\\RubyProcessor.java",
            "target": "D:\\desktop\\git-data\\depends\\5ddfc9e8ec6791a95895138f084e042cd116ff8b\\old\\src\\main\\java\\depends\\relations\\ImportLookupStrategy.java",
            "label": "Import: 1.0, Return: 1.0, ",
            "Import": 1.0,
            "Return": 1.0
        },
        {
            "source": "D:\\desktop\\git-data\\depends\\5ddfc9e8ec6791a95895138f084e042cd116ff8b\\old\\src\\main\\java\\depends\\relations\\ImportLookupStrategy.java",
            "target": "D:\\desktop\\git-data\\depends\\5ddfc9e8ec6791a95895138f084e042cd116ff8b\\old\\src\\main\\java\\depends\\relations\\Inferer.java",
            "label": "Parameter: 1.0, ",
            "Parameter": 1.0
        },
        {
            "source": "D:\\desktop\\git-data\\depends\\5ddfc9e8ec6791a95895138f084e042cd116ff8b\\old\\src\\main\\java\\depends\\relations\\Inferer.java",
            "target": "D:\\desktop\\git-data\\depends\\5ddfc9e8ec6791a95895138f084e042cd116ff8b\\old\\src\\main\\java\\depends\\extractor\\AbstractLangProcessor.java",
            "label": "Import: 1.0, Parameter: 1.0, ",
            "Import": 1.0,
            "Parameter": 1.0
        },
        {
            "source": "D:\\desktop\\git-data\\depends\\5ddfc9e8ec6791a95895138f084e042cd116ff8b\\old\\src\\main\\java\\depends\\relations\\Inferer.java",
            "target": "D:\\desktop\\git-data\\depends\\5ddfc9e8ec6791a95895138f084e042cd116ff8b\\old\\src\\main\\java\\depends\\relations\\ImportLookupStrategy.java",
            "label": "Call: 5.0, Use: 1.0, Parameter: 1.0, Contain: 1.0, ",
            "Call": 5.0,
            "Use": 1.0,
            "Parameter": 1.0,
            "Contain": 1.0
        },
        {
            "source": "D:\\desktop\\git-data\\depends\\5ddfc9e8ec6791a95895138f084e042cd116ff8b\\old\\src\\test\\java\\depends\\extractor\\cpp\\CppParserTest.java",
            "target": "D:\\desktop\\git-data\\depends\\5ddfc9e8ec6791a95895138f084e042cd116ff8b\\old\\src\\main\\java\\depends\\extractor\\cpp\\CppImportLookupStrategy.java",
            "label": "Call: 1.0, Create: 1.0, ",
            "Call": 1.0,
            "Create": 1.0
        },
        {
            "source": "D:\\desktop\\git-data\\depends\\5ddfc9e8ec6791a95895138f084e042cd116ff8b\\old\\src\\test\\java\\depends\\extractor\\cpp\\CppParserTest.java",
            "target": "D:\\desktop\\git-data\\depends\\5ddfc9e8ec6791a95895138f084e042cd116ff8b\\old\\src\\main\\java\\depends\\relations\\Inferer.java",
            "label": "Call: 1.0, Import: 1.0, Use: 1.0, Create: 1.0, Contain: 1.0, ",
            "Call": 1.0,
            "Import": 1.0,
            "Use": 1.0,
            "Create": 1.0,
            "Contain": 1.0
        },
        {
            "source": "D:\\desktop\\git-data\\depends\\5ddfc9e8ec6791a95895138f084e042cd116ff8b\\old\\src\\test\\java\\depends\\extractor\\golang\\GolangParserTest.java",
            "target": "D:\\desktop\\git-data\\depends\\5ddfc9e8ec6791a95895138f084e042cd116ff8b\\old\\src\\main\\java\\depends\\extractor\\golang\\GoImportLookupStrategy.java",
            "label": "Call: 1.0, Create: 1.0, ",
            "Call": 1.0,
            "Create": 1.0
        },
        {
            "source": "D:\\desktop\\git-data\\depends\\5ddfc9e8ec6791a95895138f084e042cd116ff8b\\old\\src\\test\\java\\depends\\extractor\\golang\\GolangParserTest.java",
            "target": "D:\\desktop\\git-data\\depends\\5ddfc9e8ec6791a95895138f084e042cd116ff8b\\old\\src\\main\\java\\depends\\relations\\Inferer.java",
            "label": "Call: 1.0, Import: 1.0, Use: 1.0, Create: 1.0, Contain: 1.0, ",
            "Call": 1.0,
            "Import": 1.0,
            "Use": 1.0,
            "Create": 1.0,
            "Contain": 1.0
        },
        {
            "source": "D:\\desktop\\git-data\\depends\\5ddfc9e8ec6791a95895138f084e042cd116ff8b\\old\\src\\test\\java\\depends\\extractor\\java\\JavaParserTest.java",
            "target": "D:\\desktop\\git-data\\depends\\5ddfc9e8ec6791a95895138f084e042cd116ff8b\\old\\src\\main\\java\\depends\\extractor\\java\\JavaImportLookupStrategy.java",
            "label": "Call: 1.0, Create: 1.0, ",
            "Call": 1.0,
            "Create": 1.0
        },
        {
            "source": "D:\\desktop\\git-data\\depends\\5ddfc9e8ec6791a95895138f084e042cd116ff8b\\old\\src\\test\\java\\depends\\extractor\\java\\JavaParserTest.java",
            "target": "D:\\desktop\\git-data\\depends\\5ddfc9e8ec6791a95895138f084e042cd116ff8b\\old\\src\\main\\java\\depends\\relations\\Inferer.java",
            "label": "Call: 1.0, Import: 1.0, Use: 1.0, Create: 1.0, Contain: 1.0, ",
            "Call": 1.0,
            "Import": 1.0,
            "Use": 1.0,
            "Create": 1.0,
            "Contain": 1.0
        },
        {
            "source": "D:\\desktop\\git-data\\depends\\5ddfc9e8ec6791a95895138f084e042cd116ff8b\\old\\src\\test\\java\\depends\\extractor\\ruby\\RubyParserTest.java",
            "target": "D:\\desktop\\git-data\\depends\\5ddfc9e8ec6791a95895138f084e042cd116ff8b\\old\\src\\main\\java\\depends\\extractor\\ruby\\RubyImportLookupStrategy.java",
            "label": "Call: 1.0, Create: 1.0, ",
            "Call": 1.0,
            "Create": 1.0
        },
        {
            "source": "D:\\desktop\\git-data\\depends\\5ddfc9e8ec6791a95895138f084e042cd116ff8b\\old\\src\\test\\java\\depends\\extractor\\ruby\\RubyParserTest.java",
            "target": "D:\\desktop\\git-data\\depends\\5ddfc9e8ec6791a95895138f084e042cd116ff8b\\old\\src\\main\\java\\depends\\relations\\Inferer.java",
            "label": "Call: 1.0, Import: 1.0, Use: 1.0, Create: 1.0, Contain: 1.0, ",
            "Call": 1.0,
            "Import": 1.0,
            "Use": 1.0,
            "Create": 1.0,
            "Contain": 1.0
        }
    ]
}