{
  "schemaVersion": "1.0",
  "name": "output-file-sdsm",
  "variables": [
    "D:\\desktop\\git-data\\depends\\1d52a169b376302d9f452bb6f6c0370b3c840a38\\new\\src\\main\\java\\depends\\Main.javaMain.java",
    "D:\\desktop\\git-data\\depends\\1d52a169b376302d9f452bb6f6c0370b3c840a38\\new\\src\\main\\java\\depends\\extractor\\AbstractLangProcessor.javaAbstractLangProcessor.java",
    "D:\\desktop\\git-data\\depends\\1d52a169b376302d9f452bb6f6c0370b3c840a38\\new\\src\\main\\java\\depends\\format\\AbstractFormatDependencyDumper.javaAbstractFormatDependencyDumper.java",
    "D:\\desktop\\git-data\\depends\\1d52a169b376302d9f452bb6f6c0370b3c840a38\\new\\src\\main\\java\\depends\\format\\DependencyDumper.javaDependencyDumper.java",
    "D:\\desktop\\git-data\\depends\\1d52a169b376302d9f452bb6f6c0370b3c840a38\\new\\src\\main\\java\\depends\\format\\detail\\DetailTextFormatDependencyDumper.javaDetailTextFormatDependencyDumper.java",
    "D:\\desktop\\git-data\\depends\\1d52a169b376302d9f452bb6f6c0370b3c840a38\\new\\src\\main\\java\\depends\\format\\dot\\DotFormatDependencyDumper.javaDotFormatDependencyDumper.java",
    "D:\\desktop\\git-data\\depends\\1d52a169b376302d9f452bb6f6c0370b3c840a38\\new\\src\\main\\java\\depends\\format\\excel\\ExcelFormatDependencyDumper.javaExcelFormatDependencyDumper.java",
    "D:\\desktop\\git-data\\depends\\1d52a169b376302d9f452bb6f6c0370b3c840a38\\new\\src\\main\\java\\depends\\format\\json\\JDataBuilder.javaJDataBuilder.java",
    "D:\\desktop\\git-data\\depends\\1d52a169b376302d9f452bb6f6c0370b3c840a38\\new\\src\\main\\java\\depends\\format\\json\\JsonFormatDependencyDumper.javaJsonFormatDependencyDumper.java",
    "D:\\desktop\\git-data\\depends\\1d52a169b376302d9f452bb6f6c0370b3c840a38\\new\\src\\main\\java\\depends\\format\\plantuml\\PlantUmlFormatDependencyDumper.javaPlantUmlFormatDependencyDumper.java",
    "D:\\desktop\\git-data\\depends\\1d52a169b376302d9f452bb6f6c0370b3c840a38\\new\\src\\main\\java\\depends\\format\\xml\\XDataBuilder.javaXDataBuilder.java",
    "D:\\desktop\\git-data\\depends\\1d52a169b376302d9f452bb6f6c0370b3c840a38\\new\\src\\main\\java\\depends\\format\\xml\\XmlFormatDependencyDumper.javaXmlFormatDependencyDumper.java",
    "D:\\desktop\\git-data\\depends\\1d52a169b376302d9f452bb6f6c0370b3c840a38\\new\\src\\main\\java\\depends\\generator\\DependencyGenerator.javaDependencyGenerator.java",
    "D:\\desktop\\git-data\\depends\\1d52a169b376302d9f452bb6f6c0370b3c840a38\\new\\src\\main\\java\\depends\\generator\\FileDependencyGenerator.javaFileDependencyGenerator.java",
    "D:\\desktop\\git-data\\depends\\1d52a169b376302d9f452bb6f6c0370b3c840a38\\new\\src\\main\\java\\depends\\generator\\FunctionDependencyGenerator.javaFunctionDependencyGenerator.java",
    "D:\\desktop\\git-data\\depends\\1d52a169b376302d9f452bb6f6c0370b3c840a38\\new\\src\\main\\java\\depends\\matrix\\core\\DependencyMatrix.javaDependencyMatrix.java",
    "D:\\desktop\\git-data\\depends\\1d52a169b376302d9f452bb6f6c0370b3c840a38\\new\\src\\main\\java\\depends\\matrix\\core\\DependencyPair.javaDependencyPair.java",
    "D:\\desktop\\git-data\\depends\\1d52a169b376302d9f452bb6f6c0370b3c840a38\\new\\src\\main\\java\\depends\\matrix\\core\\DependencyValue.javaDependencyValue.java",
    "D:\\desktop\\git-data\\depends\\1d52a169b376302d9f452bb6f6c0370b3c840a38\\new\\src\\main\\java\\depends\\matrix\\transform\\MatrixLevelReducer.javaMatrixLevelReducer.java",
    "D:\\desktop\\git-data\\depends\\1d52a169b376302d9f452bb6f6c0370b3c840a38\\new\\src\\main\\java\\depends\\matrix\\transform\\OrderedMatrixGenerator.javaOrderedMatrixGenerator.java",
    "D:\\desktop\\git-data\\depends\\1d52a169b376302d9f452bb6f6c0370b3c840a38\\new\\src\\main\\java\\depends\\matrix\\transform\\strip\\EmptyLeadingNameStripper.javaEmptyLeadingNameStripper.java",
    "D:\\desktop\\git-data\\depends\\1d52a169b376302d9f452bb6f6c0370b3c840a38\\new\\src\\main\\java\\depends\\matrix\\transform\\strip\\ILeadingNameStrippper.javaILeadingNameStrippper.java",
    "D:\\desktop\\git-data\\depends\\1d52a169b376302d9f452bb6f6c0370b3c840a38\\new\\src\\main\\java\\depends\\matrix\\transform\\strip\\LeadingNameStripper.javaLeadingNameStripper.java",
    "D:\\desktop\\git-data\\depends\\1d52a169b376302d9f452bb6f6c0370b3c840a38\\new\\src\\test\\java\\depends\\extractor\\cpp\\ForwardDeclareTest.javaForwardDeclareTest.java",
    "D:\\desktop\\git-data\\depends\\1d52a169b376302d9f452bb6f6c0370b3c840a38\\new\\src\\test\\java\\depends\\matrix\\MatrixLevelReducerTest.javaMatrixLevelReducerTest.java"
  ],
  "cells": [
    {
      "src": 0,
      "dest": 1,
      "values": {
        "Call": 3.0,
        "Import": 1.0,
        "Contain": 1.0
      }
    },
    {
      "src": 0,
      "dest": 3,
      "values": {
        "Call": 2.0,
        "Import": 1.0,
        "Create": 1.0,
        "Contain": 1.0
      }
    },
    {
      "src": 0,
      "dest": 12,
      "values": {
        "Call": 1.0,
        "Import": 1.0,
        "Contain": 1.0
      }
    },
    {
      "src": 0,
      "dest": 13,
      "values": {
        "Call": 1.0,
        "Import": 1.0,
        "Create": 1.0
      }
    },
    {
      "src": 0,
      "dest": 14,
      "values": {
        "Call": 1.0,
        "Import": 1.0,
        "Use": 1.0,
        "Create": 1.0
      }
    },
    {
      "src": 0,
      "dest": 15,
      "values": {
        "Call": 1.0,
        "Import": 1.0,
        "Use": 1.0,
        "Contain": 1.0
      }
    },
    {
      "src": 0,
      "dest": 18,
      "values": {
        "Call": 2.0,
        "Import": 1.0,
        "Create": 1.0
      }
    },
    {
      "src": 0,
      "dest": 22,
      "values": {
        "Call": 1.0,
        "Import": 1.0,
        "Create": 1.0
      }
    },
    {
      "src": 1,
      "dest": 12,
      "values": {
        "Call": 1.0,
        "Import": 1.0,
        "Use": 1.0,
        "Parameter": 1.0,
        "Contain": 1.0
      }
    },
    {
      "src": 1,
      "dest": 15,
      "values": {
        "Import": 1.0,
        "Return": 1.0,
        "Use": 2.0,
        "Contain": 1.0
      }
    },
    {
      "src": 1,
      "dest": 19,
      "values": {
        "Call": 2.0,
        "Import": 1.0,
        "Create": 1.0
      }
    },
    {
      "src": 2,
      "dest": 15,
      "values": {
        "Import": 1.0,
        "Use": 1.0,
        "Parameter": 1.0,
        "Contain": 1.0
      }
    },
    {
      "src": 3,
      "dest": 2,
      "values": {
        "Call": 3.0,
        "Create": 1.0,
        "Contain": 2.0
      }
    },
    {
      "src": 3,
      "dest": 4,
      "values": {
        "Call": 1.0,
        "Import": 1.0,
        "Create": 1.0
      }
    },
    {
      "src": 3,
      "dest": 5,
      "values": {
        "Call": 1.0,
        "Import": 1.0,
        "Create": 1.0
      }
    },
    {
      "src": 3,
      "dest": 6,
      "values": {
        "Call": 1.0,
        "Import": 1.0,
        "Create": 1.0
      }
    },
    {
      "src": 3,
      "dest": 8,
      "values": {
        "Call": 1.0,
        "Import": 1.0,
        "Create": 1.0
      }
    },
    {
      "src": 3,
      "dest": 9,
      "values": {
        "Call": 1.0,
        "Import": 1.0,
        "Create": 1.0
      }
    },
    {
      "src": 3,
      "dest": 11,
      "values": {
        "Call": 1.0,
        "Import": 1.0,
        "Create": 1.0
      }
    },
    {
      "src": 3,
      "dest": 15,
      "values": {
        "Import": 1.0,
        "Use": 1.0,
        "Parameter": 1.0,
        "Contain": 1.0
      }
    },
    {
      "src": 4,
      "dest": 2,
      "values": {
        "Call": 2.0,
        "Import": 1.0,
        "Extend": 1.0,
        "Use": 2.0
      }
    },
    {
      "src": 4,
      "dest": 15,
      "values": {
        "Call": 2.0,
        "Import": 1.0,
        "Parameter": 1.0
      }
    },
    {
      "src": 4,
      "dest": 16,
      "values": {
        "Call": 3.0,
        "Import": 1.0,
        "Use": 1.0,
        "Parameter": 1.0,
        "Contain": 1.0
      }
    },
    {
      "src": 4,
      "dest": 17,
      "values": {
        "Call": 2.0,
        "Import": 1.0,
        "Contain": 1.0
      }
    },
    {
      "src": 5,
      "dest": 2,
      "values": {
        "Call": 2.0,
        "Import": 1.0,
        "Extend": 1.0,
        "Use": 2.0
      }
    },
    {
      "src": 5,
      "dest": 15,
      "values": {
        "Call": 2.0,
        "Import": 1.0,
        "Parameter": 1.0
      }
    },
    {
      "src": 5,
      "dest": 16,
      "values": {
        "Call": 2.0,
        "Import": 1.0,
        "Use": 1.0,
        "Parameter": 1.0,
        "Contain": 1.0
      }
    },
    {
      "src": 6,
      "dest": 2,
      "values": {
        "Call": 2.0,
        "Import": 1.0,
        "Extend": 1.0,
        "Use": 7.0
      }
    },
    {
      "src": 6,
      "dest": 15,
      "values": {
        "Call": 7.0,
        "Import": 1.0,
        "Parameter": 1.0
      }
    },
    {
      "src": 6,
      "dest": 16,
      "values": {
        "Call": 3.0,
        "Import": 1.0,
        "Use": 1.0,
        "Parameter": 1.0,
        "Contain": 1.0
      }
    },
    {
      "src": 6,
      "dest": 17,
      "values": {
        "Call": 2.0,
        "Import": 1.0,
        "Contain": 1.0
      }
    },
    {
      "src": 7,
      "dest": 15,
      "values": {
        "Call": 2.0,
        "Import": 1.0,
        "Parameter": 1.0
      }
    },
    {
      "src": 7,
      "dest": 16,
      "values": {
        "Call": 3.0,
        "Import": 1.0,
        "Use": 1.0,
        "Parameter": 1.0,
        "Contain": 1.0
      }
    },
    {
      "src": 7,
      "dest": 17,
      "values": {
        "Call": 2.0,
        "Import": 1.0,
        "Contain": 1.0
      }
    },
    {
      "src": 8,
      "dest": 2,
      "values": {
        "Call": 2.0,
        "Import": 1.0,
        "Extend": 1.0,
        "Use": 2.0
      }
    },
    {
      "src": 8,
      "dest": 7,
      "values": {
        "Call": 2.0,
        "Create": 1.0,
        "Contain": 1.0
      }
    },
    {
      "src": 8,
      "dest": 15,
      "values": {
        "Import": 1.0,
        "Parameter": 1.0
      }
    },
    {
      "src": 9,
      "dest": 2,
      "values": {
        "Call": 2.0,
        "Import": 1.0,
        "Extend": 1.0,
        "Use": 3.0
      }
    },
    {
      "src": 9,
      "dest": 15,
      "values": {
        "Call": 3.0,
        "Import": 1.0,
        "Parameter": 1.0
      }
    },
    {
      "src": 9,
      "dest": 16,
      "values": {
        "Call": 3.0,
        "Import": 1.0,
        "Use": 1.0,
        "Parameter": 1.0,
        "Contain": 1.0
      }
    },
    {
      "src": 9,
      "dest": 17,
      "values": {
        "Call": 1.0,
        "Import": 1.0,
        "Contain": 1.0
      }
    },
    {
      "src": 10,
      "dest": 15,
      "values": {
        "Call": 2.0,
        "Import": 1.0,
        "Parameter": 1.0
      }
    },
    {
      "src": 10,
      "dest": 16,
      "values": {
        "Call": 3.0,
        "Import": 1.0,
        "Use": 1.0,
        "Parameter": 1.0,
        "Contain": 1.0
      }
    },
    {
      "src": 10,
      "dest": 17,
      "values": {
        "Call": 2.0,
        "Import": 1.0,
        "Contain": 1.0
      }
    },
    {
      "src": 11,
      "dest": 2,
      "values": {
        "Call": 2.0,
        "Import": 1.0,
        "Extend": 1.0,
        "Use": 2.0
      }
    },
    {
      "src": 11,
      "dest": 10,
      "values": {
        "Call": 2.0,
        "Create": 1.0,
        "Contain": 1.0
      }
    },
    {
      "src": 11,
      "dest": 15,
      "values": {
        "Import": 1.0,
        "Parameter": 1.0
      }
    },
    {
      "src": 12,
      "dest": 15,
      "values": {
        "Import": 1.0,
        "Return": 1.0
      }
    },
    {
      "src": 12,
      "dest": 20,
      "values": {
        "Call": 1.0,
        "Import": 1.0,
        "Create": 1.0
      }
    },
    {
      "src": 12,
      "dest": 21,
      "values": {
        "Import": 1.0,
        "Use": 1.0,
        "Parameter": 1.0,
        "Contain": 1.0
      }
    },
    {
      "src": 13,
      "dest": 12,
      "values": {
        "Call": 2.0,
        "Extend": 1.0,
        "Use": 1.0
      }
    },
    {
      "src": 13,
      "dest": 15,
      "values": {
        "Call": 4.0,
        "Import": 1.0,
        "Return": 1.0,
        "Create": 1.0,
        "Contain": 1.0
      }
    },
    {
      "src": 13,
      "dest": 21,
      "values": {
        "Call": 1.0
      }
    },
    {
      "src": 14,
      "dest": 12,
      "values": {
        "Call": 1.0,
        "Extend": 1.0,
        "Use": 1.0
      }
    },
    {
      "src": 14,
      "dest": 15,
      "values": {
        "Call": 3.0,
        "Import": 1.0,
        "Return": 1.0,
        "Create": 1.0,
        "Contain": 1.0
      }
    },
    {
      "src": 14,
      "dest": 21,
      "values": {
        "Call": 1.0
      }
    },
    {
      "src": 15,
      "dest": 16,
      "values": {
        "Call": 5.0,
        "Use": 4.0,
        "Create": 1.0,
        "Parameter": 1.0,
        "Contain": 1.0
      }
    },
    {
      "src": 16,
      "dest": 17,
      "values": {
        "Call": 2.0,
        "Use": 1.0,
        "Create": 1.0,
        "Parameter": 1.0,
        "Contain": 1.0
      }
    },
    {
      "src": 18,
      "dest": 15,
      "values": {
        "Call": 6.0,
        "Import": 1.0,
        "Return": 1.0,
        "Use": 1.0,
        "Create": 1.0,
        "Parameter": 1.0,
        "Contain": 2.0
      }
    },
    {
      "src": 18,
      "dest": 16,
      "values": {
        "Call": 3.0,
        "Import": 1.0,
        "Contain": 1.0
      }
    },
    {
      "src": 18,
      "dest": 17,
      "values": {
        "Call": 3.0,
        "Import": 1.0,
        "Contain": 1.0
      }
    },
    {
      "src": 19,
      "dest": 15,
      "values": {
        "Call": 6.0,
        "Import": 1.0,
        "Return": 1.0,
        "Use": 1.0,
        "Create": 1.0,
        "Parameter": 1.0,
        "Contain": 2.0
      }
    },
    {
      "src": 19,
      "dest": 16,
      "values": {
        "Call": 3.0,
        "Import": 1.0,
        "Contain": 1.0
      }
    },
    {
      "src": 19,
      "dest": 17,
      "values": {
        "Call": 3.0,
        "Import": 1.0,
        "Contain": 1.0
      }
    },
    {
      "src": 20,
      "dest": 21,
      "values": {
        "Implement": 1.0
      }
    },
    {
      "src": 22,
      "dest": 21,
      "values": {
        "Implement": 1.0
      }
    },
    {
      "src": 23,
      "dest": 13,
      "values": {
        "Call": 2.0,
        "Import": 1.0,
        "Create": 1.0,
        "Contain": 1.0
      }
    },
    {
      "src": 24,
      "dest": 18,
      "values": {
        "Call": 6.0,
        "Import": 1.0,
        "Use": 6.0
      }
    }
  ]
}