{
  "schemaVersion" : "1.0",
  "name" : "output-file-sdsm",
  "variables" : [ "D:\\desktop\\git-data\\depends\\ff26192c2be15023d7081348a59f01833bf64f06\\new\\src\\main\\java\\depends\\extractor\\pomPomFileParser.java", "D:\\desktop\\git-data\\depends\\ff26192c2be15023d7081348a59f01833bf64f06\\new\\src\\test\\java\\depends\\extractor\\pomDependencyWithPropertiesOfParentTest.java" ],
  "cells" : [ {
    "src" : 1,
    "dest" : 0,
    "values" : {
      "Call" : 2.0,
      "Contain" : 2.0
    }
  } ]
}