{
  "schemaVersion" : "1.0",
  "name" : "output-file-sdsm",
  "variables" : [ "D:\\desktop\\git-data\\depends\\910f31e4f279f89f9e62d90e5ea98ceaa6eb50c4\\old\\src\\main\\java\\depends\\entityEntity.java", "D:\\desktop\\git-data\\depends\\910f31e4f279f89f9e62d90e5ea98ceaa6eb50c4\\old\\src\\main\\java\\depends\\entityFileEntity.java", "D:\\desktop\\git-data\\depends\\910f31e4f279f89f9e62d90e5ea98ceaa6eb50c4\\old\\src\\main\\java\\depends\\extractorHandlerContext.java", "D:\\desktop\\git-data\\depends\\910f31e4f279f89f9e62d90e5ea98ceaa6eb50c4\\old\\src\\main\\java\\depends\\extractor\\cppCppHandlerContext.java", "D:\\desktop\\git-data\\depends\\910f31e4f279f89f9e62d90e5ea98ceaa6eb50c4\\old\\src\\main\\java\\depends\\extractor\\golangGoHandlerContext.java", "D:\\desktop\\git-data\\depends\\910f31e4f279f89f9e62d90e5ea98ceaa6eb50c4\\old\\src\\main\\java\\depends\\extractor\\javaJavaHandlerContext.java", "D:\\desktop\\git-data\\depends\\910f31e4f279f89f9e62d90e5ea98ceaa6eb50c4\\old\\src\\main\\java\\depends\\extractor\\kotlinKotlinHandlerContext.java", "D:\\desktop\\git-data\\depends\\910f31e4f279f89f9e62d90e5ea98ceaa6eb50c4\\old\\src\\main\\java\\depends\\extractor\\pomPomHandlerContext.java", "D:\\desktop\\git-data\\depends\\910f31e4f279f89f9e62d90e5ea98ceaa6eb50c4\\old\\src\\main\\java\\depends\\extractor\\pythonPythonBuiltInType.java", "D:\\desktop\\git-data\\depends\\910f31e4f279f89f9e62d90e5ea98ceaa6eb50c4\\old\\src\\main\\java\\depends\\extractor\\pythonPythonHandlerContext.java", "D:\\desktop\\git-data\\depends\\910f31e4f279f89f9e62d90e5ea98ceaa6eb50c4\\old\\src\\main\\java\\depends\\extractor\\python\\unionPythonCodeListener.java", "D:\\desktop\\git-data\\depends\\910f31e4f279f89f9e62d90e5ea98ceaa6eb50c4\\old\\src\\main\\java\\depends\\extractor\\rubyRubyHandlerContext.java", "D:\\desktop\\git-data\\depends\\910f31e4f279f89f9e62d90e5ea98ceaa6eb50c4\\old\\src\\test\\java\\depends\\extractor\\pythonPythonImportTest.java", "D:\\desktop\\git-data\\depends\\910f31e4f279f89f9e62d90e5ea98ceaa6eb50c4\\old\\src\\test\\java\\depends\\extractor\\pythonPythonParserTest.java", "D:\\desktop\\git-data\\depends\\910f31e4f279f89f9e62d90e5ea98ceaa6eb50c4\\old\\src\\test\\java\\depends\\extractor\\pythonShouldGetRelationInSamePackageTest.java" ],
  "cells" : [ {
    "src" : 12,
    "dest" : 0,
    "values" : {
      "Import" : 1.0,
      "Contain" : 8.0
    }
  }, {
    "src" : 6,
    "dest" : 5,
    "values" : {
      "Call" : 1.0,
      "Import" : 1.0,
      "Extend" : 1.0
    }
  }, {
    "src" : 1,
    "dest" : 0,
    "values" : {
      "Call" : 3.0,
      "Return" : 1.0,
      "Use" : 3.0,
      "Parameter" : 3.0,
      "Contain" : 2.0
    }
  }, {
    "src" : 12,
    "dest" : 1,
    "values" : {
      "Cast" : 1.0,
      "Import" : 1.0,
      "Contain" : 1.0
    }
  }, {
    "src" : 5,
    "dest" : 0,
    "values" : {
      "Call" : 1.0,
      "Import" : 1.0,
      "Return" : 1.0,
      "Use" : 1.0,
      "Contain" : 1.0
    }
  }, {
    "src" : 5,
    "dest" : 2,
    "values" : {
      "Call" : 1.0,
      "Import" : 1.0,
      "Extend" : 1.0,
      "Use" : 4.0
    }
  }, {
    "src" : 12,
    "dest" : 13,
    "values" : {
      "Call" : 34.0,
      "Extend" : 1.0,
      "Use" : 1.0
    }
  }, {
    "src" : 2,
    "dest" : 1,
    "values" : {
      "Cast" : 2.0,
      "Call" : 3.0,
      "Return" : 2.0,
      "Use" : 4.0,
      "Create" : 1.0,
      "Contain" : 1.0
    }
  }, {
    "src" : 11,
    "dest" : 2,
    "values" : {
      "Call" : 9.0,
      "Import" : 1.0,
      "Extend" : 1.0,
      "Use" : 3.0
    }
  }, {
    "src" : 2,
    "dest" : 0,
    "values" : {
      "Call" : 2.0,
      "Return" : 2.0,
      "Use" : 1.0,
      "Parameter" : 4.0,
      "Contain" : 8.0
    }
  }, {
    "src" : 7,
    "dest" : 2,
    "values" : {
      "Call" : 1.0,
      "Import" : 1.0,
      "Extend" : 1.0
    }
  }, {
    "src" : 11,
    "dest" : 0,
    "values" : {
      "Import" : 1.0,
      "Return" : 1.0,
      "Use" : 1.0,
      "Contain" : 1.0
    }
  }, {
    "src" : 14,
    "dest" : 13,
    "values" : {
      "Call" : 4.0,
      "Extend" : 1.0,
      "Use" : 1.0
    }
  }, {
    "src" : 10,
    "dest" : 2,
    "values" : {
      "Call" : 20.0
    }
  }, {
    "src" : 3,
    "dest" : 2,
    "values" : {
      "Call" : 9.0,
      "Import" : 1.0,
      "Extend" : 1.0,
      "Use" : 15.0
    }
  }, {
    "src" : 3,
    "dest" : 1,
    "values" : {
      "Call" : 1.0,
      "Return" : 1.0,
      "Use" : 1.0,
      "Create" : 1.0
    }
  }, {
    "src" : 10,
    "dest" : 1,
    "values" : {
      "Cast" : 2.0,
      "Contain" : 1.0
    }
  }, {
    "src" : 3,
    "dest" : 0,
    "values" : {
      "Return" : 1.0
    }
  }, {
    "src" : 10,
    "dest" : 0,
    "values" : {
      "Call" : 10.0,
      "Use" : 1.0,
      "Contain" : 4.0
    }
  }, {
    "src" : 10,
    "dest" : 9,
    "values" : {
      "Call" : 5.0,
      "Import" : 1.0,
      "Use" : 1.0,
      "Create" : 1.0,
      "Contain" : 1.0
    }
  }, {
    "src" : 9,
    "dest" : 0,
    "values" : {
      "Call" : 4.0,
      "Import" : 1.0,
      "Parameter" : 3.0,
      "Contain" : 2.0
    }
  }, {
    "src" : 9,
    "dest" : 2,
    "values" : {
      "Call" : 4.0,
      "Import" : 1.0,
      "Extend" : 1.0,
      "Use" : 3.0
    }
  }, {
    "src" : 4,
    "dest" : 0,
    "values" : {
      "Call" : 1.0,
      "Import" : 1.0,
      "Return" : 1.0,
      "Use" : 1.0,
      "Contain" : 1.0
    }
  }, {
    "src" : 4,
    "dest" : 2,
    "values" : {
      "Call" : 1.0,
      "Import" : 1.0,
      "Extend" : 1.0,
      "Use" : 4.0
    }
  } ]
}