{
  "directed": true,
  "multigraph": false,
  "graph": {},
  "nodes": [
    {
      "id": "D:\\desktop\\git-data\\depends\\9ed5133e6ab061c2dc983f1c1a32f37503f3ca06\\old\\src\\main\\java\\depends\\extractor\\cpp\\g4\\Antlr4CppFileParser.java"
    },
    {
      "id": "D:\\desktop\\git-data\\depends\\9ed5133e6ab061c2dc983f1c1a32f37503f3ca06\\old\\src\\main\\java\\depends\\extractor\\cpp\\g4\\CppEntitiesListener.java"
    },
    {
      "id": "D:\\desktop\\git-data\\depends\\9ed5133e6ab061c2dc983f1c1a32f37503f3ca06\\old\\src\\main\\java\\depends\\extractor\\cpp\\g4\\helper\\DeclSpecifierHelper.java"
    },
    {
      "id": "D:\\desktop\\git-data\\depends\\9ed5133e6ab061c2dc983f1c1a32f37503f3ca06\\old\\src\\main\\java\\depends\\extractor\\cpp\\g4\\helper\\DeclaratorIdVisitor.java"
    },
    {
      "id": "D:\\desktop\\git-data\\depends\\9ed5133e6ab061c2dc983f1c1a32f37503f3ca06\\old\\src\\main\\java\\depends\\extractor\\cpp\\g4\\helper\\FunctionDeclaratorVisitor.java"
    },
    {
      "id": "D:\\desktop\\git-data\\depends\\9ed5133e6ab061c2dc983f1c1a32f37503f3ca06\\old\\src\\main\\java\\depends\\extractor\\cpp\\g4\\helper\\FunctiondefinitionContextHelper.java"
    },
    {
      "id": "D:\\desktop\\git-data\\depends\\9ed5133e6ab061c2dc983f1c1a32f37503f3ca06\\old\\src\\main\\java\\depends\\extractor\\cpp\\g4\\helper\\SimpletypespecifierContextHelper.java"
    },
    {
      "id": "D:\\desktop\\git-data\\depends\\9ed5133e6ab061c2dc983f1c1a32f37503f3ca06\\old\\src\\test\\java\\depends\\extractor\\cpp\\g4\\G4GrammarTest.java"
    }
  ],
  "links": [
    {
      "label": "Contain",
      "weight": 1.0,
      "source": "D:\\desktop\\git-data\\depends\\9ed5133e6ab061c2dc983f1c1a32f37503f3ca06\\old\\src\\main\\java\\depends\\extractor\\cpp\\g4\\Antlr4CppFileParser.java",
      "target": "D:\\desktop\\git-data\\depends\\9ed5133e6ab061c2dc983f1c1a32f37503f3ca06\\old\\src\\main\\java\\depends\\extractor\\cpp\\g4\\CppEntitiesListener.java"
    },
    {
      "label": "Contain",
      "weight": 1.0,
      "source": "D:\\desktop\\git-data\\depends\\9ed5133e6ab061c2dc983f1c1a32f37503f3ca06\\old\\src\\main\\java\\depends\\extractor\\cpp\\g4\\CppEntitiesListener.java",
      "target": "D:\\desktop\\git-data\\depends\\9ed5133e6ab061c2dc983f1c1a32f37503f3ca06\\old\\src\\main\\java\\depends\\extractor\\cpp\\g4\\helper\\FunctiondefinitionContextHelper.java"
    },
    {
      "label": "Contain",
      "weight": 1.0,
      "source": "D:\\desktop\\git-data\\depends\\9ed5133e6ab061c2dc983f1c1a32f37503f3ca06\\old\\src\\main\\java\\depends\\extractor\\cpp\\g4\\helper\\FunctiondefinitionContextHelper.java",
      "target": "D:\\desktop\\git-data\\depends\\9ed5133e6ab061c2dc983f1c1a32f37503f3ca06\\old\\src\\main\\java\\depends\\extractor\\cpp\\g4\\helper\\DeclSpecifierHelper.java"
    },
    {
      "label": "Contain",
      "weight": 1.0,
      "source": "D:\\desktop\\git-data\\depends\\9ed5133e6ab061c2dc983f1c1a32f37503f3ca06\\old\\src\\main\\java\\depends\\extractor\\cpp\\g4\\helper\\FunctiondefinitionContextHelper.java",
      "target": "D:\\desktop\\git-data\\depends\\9ed5133e6ab061c2dc983f1c1a32f37503f3ca06\\old\\src\\main\\java\\depends\\extractor\\cpp\\g4\\helper\\FunctionDeclaratorVisitor.java"
    }
  ]
}