{
  "schemaVersion": "1.0",
  "name": "output-file-sdsm",
  "variables": [
    "D:\\desktop\\git-data\\depends\\61edc7a615a530bdbb27d3a53d524021c890e2f6\\old\\src\\main\\java\\depends\\DependsCommand.java",
    "D:\\desktop\\git-data\\depends\\61edc7a615a530bdbb27d3a53d524021c890e2f6\\old\\src\\main\\java\\depends\\Main.java",
    "D:\\desktop\\git-data\\depends\\61edc7a615a530bdbb27d3a53d524021c890e2f6\\old\\src\\main\\java\\depends\\matrix\\transform\\strip\\LeadingNameStripper.java"
  ],
  "cells": [
    {
      "src": 1,
      "dest": 0,
      "values": {
        "Call": 29.0,
        "Create": 3.0,
        "Use": 1.0,
        "Parameter": 1.0,
        "Contain": 1.0
      }
    },
    {
      "src": 1,
      "dest": 2,
      "values": {
        "Call": 1.0,
        "Import": 1.0,
        "Create": 1.0
      }
    }
  ]
}